structlog_opinionated/__init__.py
structlog_opinionated/config.py
structlog_opinionated/opinionated_bound_logger.py
structlog_opinionated/processors.py
structlog_opinionated/py.typed
structlog_opinionated/setup.py
structlog_opinionated/vertical_console_renderer.py
structlog_opinionated-0.1.5.dist-info/WHEEL
structlog_opinionated-0.1.5.dist-info/METADATA
structlog_opinionated-0.1.5.dist-info/RECORD
