Metadata-Version: 2.3
Name: structlog-opinionated
Version: 0.1.5
Summary: Opinionated structlog configuration for long-running asyncio servers
Author: Saurabh Das
Author-email: Saurabh Das <saurabh.das@gmail.com>
License: MIT License
Requires-Dist: pydantic-settings>=2.11.0
Requires-Dist: rich>=14.2.0
Requires-Dist: structlog>=25.4.0
Requires-Python: >=3.12
Project-URL: AI Usage Guide, https://github.com/saurabhdas/structlog-opinionated/blob/main/USAGE_SUMMARY.md
Project-URL: Developer Guide, https://github.com/saurabhdas/structlog-opinionated/blob/main/CLAUDE.md
Project-URL: Documentation, https://github.com/saurabhdas/structlog-opinionated/blob/main/README.md
Project-URL: Homepage, https://github.com/saurabhdas/structlog-opinionated
Project-URL: Repository, https://github.com/saurabhdas/structlog-opinionated
